README.rst
flask_fluentd.py
setup.cfg
setup.py
Flask_fluentd.egg-info/PKG-INFO
Flask_fluentd.egg-info/SOURCES.txt
Flask_fluentd.egg-info/dependency_links.txt
Flask_fluentd.egg-info/not-zip-safe
Flask_fluentd.egg-info/requires.txt
Flask_fluentd.egg-info/top_level.txt