Metadata-Version: 1.1
Name: Flask-fluentd
Version: 0.2.1
Summary: Log fluentd events from Flask
Home-page: https://github.com/thread/flask-fluentd/archive/0.2.1.tar.gz
Author: Thread
Author-email: j+flask_fluentd@thread.com
License: MIT
Platform: any
Classifier: Environment :: Web Environment
Classifier: Intended Audience :: Developers
Classifier: License :: OSI Approved :: BSD License
Classifier: Operating System :: OS Independent
Classifier: Programming Language :: Python
Classifier: Topic :: Internet :: WWW/HTTP :: Dynamic Content
Classifier: Topic :: Software Development :: Libraries :: Python Modules
